<?xml version="1.0" encoding="utf-8"?>
<openerp>
    <data>
        <record id="view_purchase_order_pr_form" model="ir.ui.view">
            <field name="name">purchase.order.pr.form</field>
            <field name="model">purchase.order</field>
            <field name="inherit_id" ref="purchase.purchase_order_form"/>
            <field name="arch" type="xml">
                <data>
                    <button name="wkf_send_rfq" states="draft" position="before">
                        <button name="action_mark_rfq" type="object" states="procurement_request" string="Approve Procurement Request" class="oe_highlight" groups="purchase.group_purchase_manager"/>
                    </button>
                    <field name="state" widget="statusbar" statusbar_visible="draft,sent,approved,done" statusbar_colors='{"except_picking":"red","except_invoice":"red","confirmed":"blue"}' readonly="1" position="replace">
                        <field name="state" widget="statusbar" statusbar_visible="procurement_request,draft,sent,bid,confirmed,approved,done" statusbar_colors='{"except_picking":"red","except_invoice":"red","confirmed":"blue"}' readonly="1"/>
                    </field>
                    <xpath expr="//field[@name='order_line']/tree//field[@name='name']" position="after">
                        <field name="warehouse_manager_comment" />
                    </xpath>
                </data>
            </field>
        </record>
 
         <record id="fal_procurement_request_tree" model="ir.ui.view">
             <field name="name">fal.procurement.request.tree</field>
             <field name="model">purchase.order</field>
             <field name="arch" type="xml">
                 <tree fonts="bold:message_unread==True" colors="grey:state=='cancel';blue:state in ('wait','confirmed');red:state in ('except_invoice','except_picking')" string="Procurement Request" editable="top">
                     <button name="action_cancel" type="object" states="procurement_request" string="Cancel Procurement Request" icon="gtk-cancel" groups="purchase.group_purchase_manager"/>
                     <field name="id" invisible="1"/>
                     <field name="message_unread" invisible="1"/> 
                     <field name="name" string="Reference" readonly="1"/>
                     <field name="date_order" />
                     <field name="partner_id" on_change="onchange_partner_id(partner_id)" context="{'search_default_supplier':1,'default_supplier':1,'default_customer':0}" domain="[('supplier','=',True)]"/>
                     <field name="partner_ref" invisible='1'/>
                     <field domain="[('type','=','purchase')]" name="pricelist_id" groups="product.group_purchase_pricelist" on_change="onchange_pricelist(pricelist_id, context)" invisible='1'/>
                     <field name="currency_id" invisible='1'/>
                     <field name="journal_id" invisible='1'/>
                     <field name="company_id" groups="base.group_multi_company" widget="selection" invisible='1'/>
                     <field name="dest_address_id" string="Customer Address" on_change="onchange_dest_address_id(dest_address_id)" invisible="1" />
                     <field name="location_id" invisible="1"/>
                     <field name="req_product_id" on_change="onchange_req_product_id(req_product_id)" />
                     <field name="req_product_description" attrs="{'readonly': [('state','!=','procurement_request')]}" required="1" />
                     <field name="warehouse_manager_comment" />
                     <field name="req_product_qty" attrs="{'readonly': [('state','!=','procurement_request')]}"/>
                     <field name="req_uom_id" required="1" attrs="{'readonly': [('state','!=','procurement_request')]}" />
                     <field name="minimum_planned_date" invisible="context.get('quotation_only', False)"/>
                     <field name="origin"/>
                     <field name="state"/>
                     <button name="action_mark_rfq" type="object" states="procurement_request" string="Approve Procurement Request" icon="gtk-apply" groups="purchase.group_purchase_manager"/>
                 </tree>
             </field>
        </record>

        <record model="ir.ui.view" id="falpr_product_form_view_procurement_button">
            <field name="name">falpr.product.product.procurement</field>
            <field name="model">product.product</field>
            <field name="inherit_id" ref="stock.product_form_view_procurement_button"/>
            <field name="arch" type="xml">
                <data>
                    <xpath expr="//button[@name='%(stock.product_open_quants)d']" position="attributes">
                        <attribute name="name">%(action_procurement_request_wizard)d</attribute>
                        <attribute name="string">Procurement Request</attribute>
                    </xpath>
                </data>
            </field>
        </record>
        
        <record id="procurement_request" model="ir.actions.act_window">
            <field name="name">Procurement Request</field>
            <field name="type">ir.actions.act_window</field>
            <field name="res_model">purchase.order</field>
            <field name="context">{}</field>
            <field name="domain">[('state','=','procurement_request')]</field>
            <field name="view_mode">tree,graph,calendar</field>
            <field name="view_id" ref="fal_procurement_request_tree" />
            <field name="search_view_id" ref="purchase.view_purchase_order_filter"/>
            <field name="target">current</field>
            <field name="help" type="html">
              <p class="oe_view_nocontent_create">
                Click to create procurement request.
              </p>
            </field>
        </record>
        <menuitem action="procurement_request" id="menu_procurement_request"
            parent="purchase.menu_procurement_management"
            sequence="0" groups="purchase.group_purchase_manager"/>
    
        <!-- override -->
        <record id="purchase.purchase_rfq" model="ir.actions.act_window">
            <field name="name">Quotations</field>
            <field name="type">ir.actions.act_window</field>
            <field name="res_model">purchase.order</field>
            <field name="context">{'default_state': 'draft'}</field>
            <field name="domain">[('state','in',('draft','sent','confirmed'))]</field>
            <field name="view_mode">tree,form,graph,calendar</field>
            <field name="view_id" ref="purchase.purchase_order_tree" />
            <field name="search_view_id" ref="purchase.view_purchase_order_filter"/>
            <field name="help" type="html">
              <p class="oe_view_nocontent_create">
                Click to create a request for quotation.
              </p><p>
                The quotation contains the history of the discussion/negociation
                you had with your supplier. Once confirmed, a request for
                quotation is converted into a purchase order.
              </p><p>
                Most propositions of purchase orders are created automatically
                by OpenERP based on inventory needs.
              </p>
            </field>
        </record>
        <menuitem action="purchase.purchase_rfq" id="purchase.menu_purchase_rfq"
            parent="purchase.menu_procurement_management"
            sequence="1"/>

        <record id="purchase.purchase_form_action" model="ir.actions.act_window">
            <field name="name">Purchase Orders</field>
            <field name="type">ir.actions.act_window</field>
            <field name="res_model">purchase.order</field>
            <field name="view_mode">tree,form,graph,calendar</field>
            <field name="view_id" ref="purchase.purchase_order_tree" />
            <field name="context">{'default_state': 'draft'}</field>
            <field name="domain">[('state','not in',('procurement_request','draft','sent','cancel','confirmed'))]</field>
            <field name="search_view_id" ref="purchase.view_purchase_order_filter"/>
            <field name="help" type="html">
              <p class="oe_view_nocontent_create">
                Click to create a quotation that will be converted into a purchase order. 
              </p><p>
                Use this menu to search within your purchase orders by
                references, supplier, products, etc. For each purchase order,
                you can track the related discussion with the supplier, control
                the products received and control the supplier invoices.
              </p>
            </field>
        </record> 
        
        <record id="cancel_fal_purchase_form_action" model="ir.actions.act_window">
            <field name="name">Cancel Quotations</field>
            <field name="type">ir.actions.act_window</field>
            <field name="res_model">purchase.order</field>
            <field name="view_mode">tree,form,graph,calendar</field>
            <field name="view_id" ref="purchase.purchase_order_tree" />
            <field name="context">{'default_state': 'draft'}</field>
            <field name="domain">[('state','=','cancel')]</field>
            <field name="search_view_id" ref="purchase.view_purchase_order_filter"/>
            <field name="help" type="html">
              <p class="oe_view_nocontent_create">
                Click to create a quotation that will be converted into a purchase order. 
              </p><p>
                Use this menu to search within your purchase orders by
                references, supplier, products, etc. For each purchase order,
                you can track the related discussion with the supplier, control
                the products received and control the supplier invoices.
              </p>
            </field>
        </record>
            
        <menuitem action="cancel_fal_purchase_form_action" id="fal_menu_cancel_quotation"
            parent="purchase.menu_procurement_management" groups="purchase.group_purchase_user"
            sequence="7" />
    </data>
</openerp>